{
    "shareQQBean":{
        "shareQQImgUrl":"http://pic1.win4000.com/pic/8/06/ad9811544.jpg",
        "shareTitle":"PP视频",
        "shareTitleUrl":"http://cn.hk.uy/xt",
        "shareContent":"PP视频，日韩、大陆、欧美、动漫视频免费观看"
    },
     "vipDowloadUrl":"https://url.cn/5NSfX5K",
    "normalUrl":[
        {
            "item":"https://lm.qiqipip.ml/"
        },
        {
            "item":"https://lm.qiqipip.ml/"
        },
        {
            "item":"https://lm.qiqipip.ml/"
        },
        {
            "item":"https://lm.qiqipip.ml/"
        }
    ],
    "vipUrl":[ 
        {
            "item":"https://lm.qiqipip.ml/"
        },
        {
            "item":"https://lm.qiqipip.ml/"
        },
        {
            "item":"https://lm.qiqipip.ml/"
        }
    ]
}
