{
    "shareQQBean":{
        "shareQQImgUrl":"https://timgsa.baidu.com/timg?image&quality=80&size=b9999_10000&sec=1582263853677&di=d1e938b3c7c663607ee213fecd27efd0&imgtype=0&src=http%3A%2F%2Fa.hiphotos.baidu.com%2Fimage%2Fpic%2Fitem%2F472309f7905298224ae7f02dddca7bcb0b46d40c.jpg",
        "shareTitle":"PP视频",
        "shareTitleUrl":"http://cn.hk.uy/aTz",
        "shareContent":"电影、美女图片、真人直播免费观看,没时间解释了，老司机快上车！"
    },
     "vipDowloadUrl":"https://url.cn/5NSfX5K",
    "normalUrl":[
        {
            "item":"https://www.51makelove.com/"
        },
        {
            "item":"https://www.51makelove.com/"
        },
        {
            "item":"https://www.51makelove.com/"
        },
        {
            "item":"https://www.51makelove.com/"
        }
    ],
    "vipUrl":[ 
        {
            "item":"https://www.51makelove.com/"
        },
        {
            "item":"https://www.51makelove.com/"
        },
        {
            "item":"https://www.51makelove.com/"
        }
    ]
}
